gumo/__init__.py
gumo/pullqueue/__init__.py
gumo/pullqueue/domain/__init__.py
gumo/pullqueue/server/__init__.py
gumo/pullqueue/server/_configuration.py
gumo/pullqueue/server/bind.py
gumo/pullqueue/server/application/__init__.py
gumo/pullqueue/server/application/repository.py
gumo/pullqueue/server/application/enqueue/__init__.py
gumo/pullqueue/server/application/enqueue/factory.py
gumo/pullqueue/server/application/lease/__init__.py
gumo/pullqueue/server/domain/__init__.py
gumo/pullqueue/server/domain/configuration/__init__.py
gumo/pullqueue/server/infrastructure/__init__.py
gumo/pullqueue/server/infrastructure/mapper/__init__.py
gumo/pullqueue/server/infrastructure/repository/__init__.py
gumo/pullqueue/server/presentation/__init__.py
gumo/pullqueue/server/presentation/restapi/__init__.py
gumo/pullqueue/worker/__init__.py
gumo/pullqueue/worker/_configuration.py
gumo/pullqueue/worker/bind.py
gumo/pullqueue/worker/application/__init__.py
gumo/pullqueue/worker/application/repository.py
gumo/pullqueue/worker/application/service.py
gumo/pullqueue/worker/domain/__init__.py
gumo/pullqueue/worker/domain/configuration/__init__.py
gumo/pullqueue/worker/infrastructure/__init__.py
gumo/pullqueue/worker/infrastructure/repository/__init__.py
gumo/pullqueue/worker/presentation/__init__.py
gumo/pullqueue/worker/presentation/cli/__init__.py
gumo_pullqueue-0.2.1.dist-info/LICENSE
gumo_pullqueue-0.2.1.dist-info/METADATA
gumo_pullqueue-0.2.1.dist-info/WHEEL
gumo_pullqueue-0.2.1.dist-info/top_level.txt
gumo_pullqueue-0.2.1.dist-info/RECORD
