Metadata-Version: 2.1
Name: gumo-pullqueue
Version: 0.2.1
Summary: Gumo PullQueue Library
Home-page: https://github.com/gumo-py/gumo-pullqueue
Author: Gumo Project Team
Author-email: gumo-py@googlegroups.com
License: UNKNOWN
Platform: UNKNOWN
Classifier: Programming Language :: Python :: 3
Classifier: License :: OSI Approved :: MIT License
Classifier: Operating System :: OS Independent
Requires-Dist: gumo-core (>=0.1.0)
Requires-Dist: gumo-datastore (>=0.1.0)
Requires-Dist: Flask (>=1.0.2)
Requires-Dist: flasgger (>=0.9.1)
